builder/__init__.py
builder/__version__.py
builder/cli.py
builder/prompt.py
builder/data/Dockerfile
builder/data/__init__.py
builder/data/motd.txt
scioer_builder-0.16.0.dist-info/LICENSE
scioer_builder-0.16.0.dist-info/METADATA
scioer_builder-0.16.0.dist-info/WHEEL
scioer_builder-0.16.0.dist-info/entry_points.txt
scioer_builder-0.16.0.dist-info/top_level.txt
scioer_builder-0.16.0.dist-info/RECORD
