Metadata-Version: 2.1
Name: scioer-builder
Version: 0.16.0
Summary: A cli application to help build custom versions of the sci-oer course container
Author-email: Marshall Asch <masch@uoguelph.ca>
Project-URL: Homepage, https://github.com/sci-oer/automated-builder
Project-URL: Bug Reports, https://github.com/sci-oer/automated-builder/issues
Project-URL: Funding, https://github.com/sci-oer/automated-builder/blob/main/.github/FUNDING.md
Project-URL: Documentation, https://github.com/sci-oer/automated-builder/blob/main/README.md
Project-URL: Source, https://github.com/sci-oer/automated-builder
Classifier: Development Status :: 3 - Alpha
Classifier: Intended Audience :: Education
Classifier: Intended Audience :: Developers
Classifier: Programming Language :: Python :: 3.7
Classifier: Programming Language :: Python :: 3.8
Classifier: Programming Language :: Python :: 3.9
Classifier: Programming Language :: Python :: 3.10
Classifier: License :: OSI Approved :: GNU Affero General Public License v3
Classifier: Operating System :: OS Independent
Classifier: Topic :: Education
Classifier: Topic :: Education :: Computer Aided Instruction (CAI)
Classifier: Topic :: Software Development
Classifier: Topic :: Utilities
Requires-Python: >=3.7
License-File: LICENSE
Requires-Dist: colorlog (==6.7.0)
Requires-Dist: docker (==6.1.3)
Requires-Dist: docopt (==0.6.2)
Requires-Dist: GitPython (==3.1.32)
Requires-Dist: requests (==2.31.0)
Requires-Dist: tqdm (==4.65.0)
Requires-Dist: pyreadline3 (==3.4.1) ; platform_system == "Windows"
